myPackagesQJ1204/__init__.py
myPackagesQJ1204/aaa.py
myPackagesQJ1204-0.1.0.dist-info/LICENSE
myPackagesQJ1204-0.1.0.dist-info/METADATA
myPackagesQJ1204-0.1.0.dist-info/WHEEL
myPackagesQJ1204-0.1.0.dist-info/top_level.txt
myPackagesQJ1204-0.1.0.dist-info/RECORD
