Metadata-Version: 2.1
Name: myPackagesQJ1204
Version: 0.1.0
Summary: edited by myself
Author: xiaoxin
Classifier: Programming Language :: Python :: 3
Classifier: License :: OSI Approved :: MIT License
Classifier: Operating System :: OS Independent
Requires-Python: >=3
License-File: LICENSE
Requires-Dist: pandas
